{
    "meter": {"serialNumber": "kili"},
    "unitOfWork": {
        "serialNumber": "kili",
        "payloadDate": "2023-05-01T00:00:00Z",
        "dataStreams": [
            {
                "name": "Total",
                "interval": 5,
                "readings": [
                    {"timestamp": "2023-04-30T00:05:00Z", "value": 0.929},
                    {"timestamp": "2023-04-30T00:10:00Z", "value": 0.955},
                    {"timestamp": "2023-04-30T00:15:00Z", "value": 0.974},
                    {"timestamp": "2023-04-30T00:20:00Z", "value": 0.872},
                    {"timestamp": "2023-04-30T00:25:00Z", "value": 0.977},
                    {"timestamp": "2023-04-30T00:30:00Z", "value": 0.959},
                    {"timestamp": "2023-04-30T00:35:00Z", "value": 1.027},
                    {"timestamp": "2023-04-30T00:40:00Z", "value": 0.855},
                    {"timestamp": "2023-04-30T00:45:00Z", "value": 1.054},
                    {"timestamp": "2023-04-30T00:50:00Z", "value": 0.991},
                    {"timestamp": "2023-04-30T00:55:00Z", "value": 1.047},
                    {"timestamp": "2023-04-30T01:00:00Z", "value": 1.042},
                    {"timestamp": "2023-04-30T01:05:00Z", "value": 0.906},
                ],
            },
            {
                "name": "House",
                "interval": 5,
                "readings": [
                    {"timestamp": "2023-04-30T00:05:00Z", "value": 0.611},
                    {"timestamp": "2023-04-30T00:10:00Z", "value": 0.643},
                    {"timestamp": "2023-04-30T00:15:00Z", "value": 0.613},
                    {"timestamp": "2023-04-30T00:20:00Z", "value": 0.537},
                    {"timestamp": "2023-04-30T00:25:00Z", "value": 0.556},
                    {"timestamp": "2023-04-30T00:30:00Z", "value": 0.553},
                    {"timestamp": "2023-04-30T00:35:00Z", "value": 0.587},
                    {"timestamp": "2023-04-30T00:40:00Z", "value": 0.602},
                    {"timestamp": "2023-04-30T00:45:00Z", "value": 0.542},
                    {"timestamp": "2023-04-30T00:50:00Z", "value": 0.566},
                    {"timestamp": "2023-04-30T00:55:00Z", "value": 0.564},
                    {"timestamp": "2023-04-30T01:00:00Z", "value": 0.563},
                    {"timestamp": "2023-04-30T01:05:00Z", "value": 0.629},
                ],
            },
            {
                "name": "Garden",
                "interval": 5,
                "readings": [
                    {"timestamp": "2023-04-30T00:05:00Z", "value": 0.097},
                    {"timestamp": "2023-04-30T00:10:00Z", "value": 0.1},
                    {"timestamp": "2023-04-30T00:15:00Z", "value": 0.105},
                    {"timestamp": "2023-04-30T00:20:00Z", "value": 0.105},
                    {"timestamp": "2023-04-30T00:25:00Z", "value": 0.09},
                    {"timestamp": "2023-04-30T00:30:00Z", "value": 0.094},
                    {"timestamp": "2023-04-30T00:35:00Z", "value": 0.095},
                    {"timestamp": "2023-04-30T00:40:00Z", "value": 0.081},
                    {"timestamp": "2023-04-30T00:45:00Z", "value": 0.085},
                    {"timestamp": "2023-04-30T00:50:00Z", "value": 0.095},
                    {"timestamp": "2023-04-30T00:55:00Z", "value": 0.097},
                    {"timestamp": "2023-04-30T01:00:00Z", "value": 0.084},
                    {"timestamp": "2023-04-30T01:05:00Z", "value": 0.088},
                ],
            },
            {
                "name": "Shed",
                "interval": 5,
                "readings": [
                    {"timestamp": "2023-04-30T00:05:00Z", "value": 0.3},
                    {"timestamp": "2023-04-30T00:10:00Z", "value": 0.308},
                    {"timestamp": "2023-04-30T00:15:00Z", "value": 0.314},
                    {"timestamp": "2023-04-30T00:20:00Z", "value": 0.246},
                    {"timestamp": "2023-04-30T00:25:00Z", "value": 0.273},
                    {"timestamp": "2023-04-30T00:30:00Z", "value": 0.26},
                    {"timestamp": "2023-04-30T00:35:00Z", "value": 0.281},
                    {"timestamp": "2023-04-30T00:40:00Z", "value": 0.299},
                    {"timestamp": "2023-04-30T00:45:00Z", "value": 0.261},
                    {"timestamp": "2023-04-30T00:50:00Z", "value": 0.296},
                    {"timestamp": "2023-04-30T00:55:00Z", "value": 0.292},
                    {"timestamp": "2023-04-30T01:00:00Z", "value": 0.282},
                    {"timestamp": "2023-04-30T01:05:00Z", "value": 0.271},
                ],
            },
            {
                "name": "Wind",
                "interval": 5,
                "readings": [
                    {"timestamp": "2023-04-30T00:05:00Z", "value": 0.516},
                    {"timestamp": "2023-04-30T00:10:00Z", "value": 0.465},
                    {"timestamp": "2023-04-30T00:15:00Z", "value": 0.463},
                    {"timestamp": "2023-04-30T00:20:00Z", "value": 0.437},
                    {"timestamp": "2023-04-30T00:25:00Z", "value": 0.446},
                    {"timestamp": "2023-04-30T00:30:00Z", "value": 0.452},
                    {"timestamp": "2023-04-30T00:35:00Z", "value": 0.515},
                    {"timestamp": "2023-04-30T00:40:00Z", "value": 0.496},
                    {"timestamp": "2023-04-30T00:45:00Z", "value": 0.477},
                    {"timestamp": "2023-04-30T00:50:00Z", "value": 0.463},
                    {"timestamp": "2023-04-30T00:55:00Z", "value": 0.477},
                    {"timestamp": "2023-04-30T01:00:00Z", "value": 0.497},
                    {"timestamp": "2023-04-30T01:05:00Z", "value": 0.445},
                ],
            },
        ],
    },
}
